rostam_pack/__init__.py
rostam_pack/__main__.py
rostam_pack/hooks.py
rostam_pack/pipeline_registry.py
rostam_pack/settings.py
rostam_pack/pipelines/__init__.py
rostam_pack/pipelines/etl_app/__init__.py
rostam_pack/pipelines/etl_app/nodes.py
rostam_pack/pipelines/etl_app/pipeline.py
rostam_pack/pipelines/ml_app/__init__.py
rostam_pack/pipelines/ml_app/nodes.py
rostam_pack/pipelines/ml_app/pipeline.py
rostam_pack/pipelines/user_app/__init__.py
rostam_pack/pipelines/user_app/nodes.py
rostam_pack/pipelines/user_app/pipeline.py
tests/pipelines/__init__.py
rostam_pack-0.7.dist-info/METADATA
rostam_pack-0.7.dist-info/WHEEL
rostam_pack-0.7.dist-info/entry_points.txt
rostam_pack-0.7.dist-info/top_level.txt
rostam_pack-0.7.dist-info/RECORD
