Metadata-Version: 2.1
Name: rostam-pack
Version: 0.7
Summary: UNKNOWN
Home-page: UNKNOWN
License: UNKNOWN
Platform: UNKNOWN
Requires-Dist: black (==21.5b1)
Requires-Dist: flake8 (<4.0,>=3.7.9)
Requires-Dist: ipython (~=7.10)
Requires-Dist: isort (~=5.0)
Requires-Dist: jupyter (~=1.0)
Requires-Dist: jupyter-client (<7.0,>=5.1)
Requires-Dist: jupyterlab (~=3.0)
Requires-Dist: kedro (==0.17.7)
Requires-Dist: kedro-telemetry (~=0.1.0)
Requires-Dist: nbstripout (~=0.4)
Requires-Dist: pytest-cov (~=3.0)
Requires-Dist: pytest-mock (<2.0,>=1.7.1)
Requires-Dist: pytest (~=6.2)
Requires-Dist: wheel (<0.37,>=0.35)
Requires-Dist: kedro-mlflow (==0.8.1)
Requires-Dist: moosir-feature (==1.4)
Requires-Dist: ipython (~=7.16.3) ; python_version == "3.6"
Requires-Dist: ipython (<8.0,>=7.31.1) ; python_version > "3.6"
Provides-Extra: docs
Requires-Dist: docutils (<0.18.0) ; extra == 'docs'
Requires-Dist: sphinx (~=3.4.3) ; extra == 'docs'
Requires-Dist: sphinx-rtd-theme (==0.5.1) ; extra == 'docs'
Requires-Dist: nbsphinx (==0.8.1) ; extra == 'docs'
Requires-Dist: nbstripout (~=0.4) ; extra == 'docs'
Requires-Dist: recommonmark (==0.7.1) ; extra == 'docs'
Requires-Dist: sphinx-autodoc-typehints (==1.11.1) ; extra == 'docs'
Requires-Dist: sphinx-copybutton (==0.3.1) ; extra == 'docs'
Requires-Dist: ipykernel (<7.0,>=5.3) ; extra == 'docs'
